django_summary_admin/__init__.py
django_summary_admin/admin.py
django_summary_admin/apps.py
django_summary_admin/migrations/__init__.py
django_summary_admin/templates/change_links/change_form.html
django_summary_admin/templates/change_links/change_form_object_tools_links.html
django_summary_admin/templates/summary_admin/change_list_resume.html
django_summary_admin/templates/summary_admin/summary_change_list.html
django_summary_admin/templates/summary_admin/summary_change_list_results.html
django_summary_admin/templatetags/__init__.py
django_summary_admin/templatetags/change_form_links.py
django_summary_admin/templatetags/summary_admin.py
django_summary_admin-0.2.6.dist-info/LICENSE
django_summary_admin-0.2.6.dist-info/METADATA
django_summary_admin-0.2.6.dist-info/WHEEL
django_summary_admin-0.2.6.dist-info/top_level.txt
django_summary_admin-0.2.6.dist-info/RECORD
