Metadata-Version: 2.1
Name: django-summary-admin
Version: 0.2.6
Summary: Using summaries for totals in Django admin
Author-email: Eduardo Stefanello <eduardo@stefanello.cc>
Project-URL: Homepage, https://github.com/dudustefanello/django_summary_admin/
Classifier: Environment :: Web Environment
Classifier: Framework :: Django
Classifier: Framework :: Django :: 5.0
Classifier: Intended Audience :: Developers
Classifier: License :: OSI Approved :: BSD License
Classifier: Operating System :: OS Independent
Classifier: Programming Language :: Python
Classifier: Programming Language :: Python :: 3
Classifier: Programming Language :: Python :: 3 :: Only
Classifier: Programming Language :: Python :: 3.10
Classifier: Programming Language :: Python :: 3.11
Classifier: Programming Language :: Python :: 3.12
Classifier: Topic :: Internet :: WWW/HTTP
Classifier: Topic :: Internet :: WWW/HTTP :: Dynamic Content
Requires-Python: >=3.10
License-File: LICENSE
Requires-Dist: django >=5.0
